cmvk/__init__.py
cmvk/audit.py
cmvk/hf_utils.py
cmvk/metrics.py
cmvk/profiles.py
cmvk/py.typed
cmvk/types.py
cmvk/verification.py
cmvk-0.3.0.dist-info/METADATA
cmvk-0.3.0.dist-info/WHEEL
cmvk-0.3.0.dist-info/entry_points.txt
cmvk-0.3.0.dist-info/licenses/LICENSE
cmvk-0.3.0.dist-info/RECORD
