Metadata-Version: 2.4
Name: cmvk
Version: 0.3.0
Summary: Mathematical and adversarial verification library for calculating drift/hallucination scores between outputs
Project-URL: Homepage, https://github.com/imran-siddique/cmvk
Project-URL: Documentation, https://github.com/imran-siddique/cmvk#readme
Project-URL: Repository, https://github.com/imran-siddique/cmvk.git
Project-URL: Issues, https://github.com/imran-siddique/cmvk/issues
Project-URL: Changelog, https://github.com/imran-siddique/cmvk/blob/main/CHANGELOG.md
Author-email: Imran Siddique <imran.siddique@example.com>
License: MIT
License-File: LICENSE
Keywords: adversarial,ai-safety,drift-detection,hallucination,mathematical,scoring,verification
Classifier: Development Status :: 4 - Beta
Classifier: Intended Audience :: Developers
Classifier: Intended Audience :: Science/Research
Classifier: License :: OSI Approved :: MIT License
Classifier: Operating System :: OS Independent
Classifier: Programming Language :: Python :: 3
Classifier: Programming Language :: Python :: 3.11
Classifier: Programming Language :: Python :: 3.12
Classifier: Programming Language :: Python :: 3.13
Classifier: Topic :: Scientific/Engineering :: Artificial Intelligence
Classifier: Topic :: Software Development :: Quality Assurance
Classifier: Topic :: Software Development :: Testing
Classifier: Typing :: Typed
Requires-Python: >=3.11
Requires-Dist: numpy>=1.24.0
Provides-Extra: all
Requires-Dist: black>=24.10.0; extra == 'all'
Requires-Dist: mypy>=1.14.0; extra == 'all'
Requires-Dist: pytest-cov>=6.0.0; extra == 'all'
Requires-Dist: pytest>=8.3.0; extra == 'all'
Requires-Dist: ruff>=0.9.0; extra == 'all'
Requires-Dist: scipy>=1.11.0; extra == 'all'
Provides-Extra: dev
Requires-Dist: black>=24.10.0; extra == 'dev'
Requires-Dist: mypy>=1.14.0; extra == 'dev'
Requires-Dist: pytest-cov>=6.0.0; extra == 'dev'
Requires-Dist: pytest>=8.3.0; extra == 'dev'
Requires-Dist: ruff>=0.9.0; extra == 'dev'
Provides-Extra: scipy
Requires-Dist: scipy>=1.11.0; extra == 'scipy'
